README.md
setup.py
powerschool_client/__init__.py
powerschool_client/client.py
powerschool_client/client_helper.py
powerschool_client/errors.py
powerschool_client/tokens.py
powerschool_client/tokens_aws.py
strongmind_powerschool_client.egg-info/PKG-INFO
strongmind_powerschool_client.egg-info/SOURCES.txt
strongmind_powerschool_client.egg-info/dependency_links.txt
strongmind_powerschool_client.egg-info/top_level.txt
test/__init__.py
test/response_mocks.py
test/test_powerschool_client.py
test/test_tokens_aws.py
test/factories/__init__.py
test/factories/contact_access_fixtures.py
test/factories/powerschool_api_results.py
test/factories/student.py