Metadata-Version: 2.1
Name: strongmind-powerschool-client
Version: 2.0.4
Summary: Client for accessing PowerSchool's REST API
Home-page: https://github.com/StrongMind/powerschool-client
Author: team-platform
Author-email: cinnamon@strongmind.com
Requires-Python: >=3.6
